huaweicloudsdkkoomessage/__init__.py
huaweicloudsdkkoomessage/v1/__init__.py
huaweicloudsdkkoomessage/v1/koomessage_async_client.py
huaweicloudsdkkoomessage/v1/koomessage_client.py
huaweicloudsdkkoomessage/v1/model/__init__.py
huaweicloudsdkkoomessage/v1/model/add_aim_msg_signature_request.py
huaweicloudsdkkoomessage/v1/model/add_aim_msg_signature_response.py
huaweicloudsdkkoomessage/v1/model/add_call_back_request.py
huaweicloudsdkkoomessage/v1/model/add_call_back_response.py
huaweicloudsdkkoomessage/v1/model/add_callback_request_body.py
huaweicloudsdkkoomessage/v1/model/add_vms_call_back_request.py
huaweicloudsdkkoomessage/v1/model/add_vms_call_back_request_body.py
huaweicloudsdkkoomessage/v1/model/add_vms_call_back_response.py
huaweicloudsdkkoomessage/v1/model/aim_personal_template_content.py
huaweicloudsdkkoomessage/v1/model/aim_personal_template_content_action.py
huaweicloudsdkkoomessage/v1/model/aim_personal_template_factory.py
huaweicloudsdkkoomessage/v1/model/aim_personal_template_page.py
huaweicloudsdkkoomessage/v1/model/aim_personal_template_param.py
huaweicloudsdkkoomessage/v1/model/aim_resolve_detail.py
huaweicloudsdkkoomessage/v1/model/aim_resolve_task.py
huaweicloudsdkkoomessage/v1/model/aim_resolve_task_mode.py
huaweicloudsdkkoomessage/v1/model/aim_resolve_task_request_mode.py
huaweicloudsdkkoomessage/v1/model/aim_send_detail.py
huaweicloudsdkkoomessage/v1/model/aim_send_report.py
huaweicloudsdkkoomessage/v1/model/aim_send_task_info.py
huaweicloudsdkkoomessage/v1/model/aim_send_task_request_mode.py
huaweicloudsdkkoomessage/v1/model/aim_send_task_sms_channel.py
huaweicloudsdkkoomessage/v1/model/aim_send_tasks_mode.py
huaweicloudsdkkoomessage/v1/model/aim_template.py
huaweicloudsdkkoomessage/v1/model/aim_template_params.py
huaweicloudsdkkoomessage/v1/model/aim_template_report.py
huaweicloudsdkkoomessage/v1/model/callback.py
huaweicloudsdkkoomessage/v1/model/check_mobile_capability_request.py
huaweicloudsdkkoomessage-3.1.184.dist-info/METADATA
huaweicloudsdkkoomessage-3.1.184.dist-info/WHEEL
huaweicloudsdkkoomessage-3.1.184.dist-info/licenses/LICENSE
huaweicloudsdkkoomessage-3.1.184.dist-info/RECORD
